MANIFEST.in
README.rst
setup.py
geonames/__init__.py
geonames/compat.py
geonames/adapters/__init__.py
geonames/adapters/base.py
geonames/adapters/search.py
geonames/config/__init__.py
geonames/config/api.py
geonames/config/log.py
geonames/resources/README.rst
geonames/resources/requirements.txt
geonames/resources/scripts/gn_search
geonames_rdf.egg-info/PKG-INFO
geonames_rdf.egg-info/SOURCES.txt
geonames_rdf.egg-info/dependency_links.txt
geonames_rdf.egg-info/not-zip-safe
geonames_rdf.egg-info/requires.txt
geonames_rdf.egg-info/top_level.txt