Metadata-Version: 1.0
Name: geonames-rdf
Version: 0.2.2
Summary: Query data from geonames.org and return RDF/Semantic Web data.
Home-page: https://github.com/dsoprea/PathManifest
Author: Dustin Oprea
Author-email: myselfasunder@gmail.com
License: GPL 2
Keywords: geonames rdf
Platform: UNKNOWN
